MANIFEST.in
NEWS.rst
README.rst
setup.py
bin/capsid
capsid/__init__.py
capsid/alignment.py
capsid/colorize.py
capsid/configure.py
capsid/database.py
capsid/fasta.py
capsid/gbloader.py
capsid/intersect.py
capsid/project.py
capsid/qfilter.py
capsid/sam2bam.py
capsid/sample.py
capsid/statistics.py
capsid/subtraction.py
capsid/taxonomy.py
capsid.egg-info/PKG-INFO
capsid.egg-info/SOURCES.txt
capsid.egg-info/dependency_links.txt
capsid.egg-info/requires.txt
capsid.egg-info/top_level.txt
capsid.egg-info/zip-safe