Metadata-Version: 1.1
Name: capsid
Version: 1.6.2
Summary: CaPSID: Computational Pathogen Sequence Identification
Home-page: https://github.com/capsid/capsid
Author: Shane Wilson
Author-email: shane.wilson@oicr.on.ca
License: GNU General Public License, Version 3.0
Download-URL: https://github.com/capsid/capsid
Platform: UNKNOWN
Classifier: Development Status :: 5 - Production/Stable
Classifier: License :: OSI Approved :: GNU General Public License (GPL)
Classifier: Environment :: Console
Classifier: Intended Audience :: Science/Research
Classifier: Intended Audience :: Developers
Classifier: Programming Language :: Python :: 2.7
Classifier: Topic :: Scientific/Engineering :: Bio-Informatics
Classifier: Operating System :: Unix
